<?xml version="1.0" encoding="UTF-8"?>
<metadata xml:lang="en"><Esri><CreaDate>20200813</CreaDate><CreaTime>19533400</CreaTime><ArcGISFormat>1.0</ArcGISFormat><ArcGISstyle>FGDC CSDGM Metadata</ArcGISstyle><SyncOnce>TRUE</SyncOnce><DataProperties><lineage><Process ToolSource="c:\program files (x86)\arcgis\desktop10.7\ArcToolbox\Toolboxes\Spatial Analyst Tools.tbx\RasterCalculator" Date="20200310" Time="161104">RasterCalculator Con((("LULC_CMCC_baseline_v2.tif" != 323) &amp; ("LULC_CMCC_baseline_v2.tif" != 325)  &amp; ("Roads_processing\Roads_2011_BERDS_bg0.tif" &gt; 0)), "Roads_processing\Roads_2011_BERDS_bg0.tif","LULC_CMCC_baseline_v2.tif") D:\Belize\Caracol\model_inputs\scenarios\LULC_CMCC_baseline_v2_roads.tif</Process></lineage><itemProps><itemLocation><linkage Sync="TRUE">file://\\LAPTOP-29NPL9E4\D$\Belize\Caracol\data\CMCC_SDP_NatCap_report_data\CMCC_SDP_NatCap_report_data_zipfiles\land_use_land_cover_CMCC\LULC_CMCC_baseline_v2_roads.tif</linkage><protocol Sync="TRUE">Local Area Network</protocol></itemLocation></itemProps><copyHistory><copy source="D:\Belize\Caracol\model_inputs\SDR_inputs_CMCC_baseline_v2_roads_uncalibrated\LULC_CMCC_baseline_v2_roads.tif" dest="\\LAPTOP-29NPL9E4\D$\Belize\Caracol\data\CMCC_SDP_NatCap_report_data\CMCC_SDP_NatCap_report_data_zipfiles\land_use_land_cover_CMCC\LULC_CMCC_baseline_v2_roads.tif" date="20200813" time="19533400"></copy></copyHistory></DataProperties></Esri></metadata>
